pool_manager/__init__.py
pool_manager/manager.py
test/__init__.py
test/test_base.py
test/test_pool_manager.py
test/test_thread_manager.py
thread_manager/__init__.py
thread_manager/argument.py
thread_manager/decorator.py
thread_manager/manager.py
thread_manager_py-0.3.0.dist-info/LICENSE
thread_manager_py-0.3.0.dist-info/METADATA
thread_manager_py-0.3.0.dist-info/WHEEL
thread_manager_py-0.3.0.dist-info/top_level.txt
thread_manager_py-0.3.0.dist-info/RECORD
