Metadata-Version: 2.1
Name: thread-manager-py
Version: 0.3.0
Summary: Python Thread Manager
Home-page: https://github.com/sanggi-wjg/py-thread-manager
Author: SangGi
Author-email: girr311@naver.com
Project-URL: Bug Tracker, https://github.com/sanggi-wjg/py-thread-manager/issues
Classifier: Operating System :: OS Independent
Classifier: License :: OSI Approved :: MIT License
Classifier: Programming Language :: Python :: 3.8
Classifier: Programming Language :: Python :: 3.9
Classifier: Programming Language :: Python :: 3.10
Classifier: Programming Language :: Python :: 3.11
License-File: LICENSE
